DRecPy/__init__.py
DRecPy/Dataset/__init__.py
DRecPy/Dataset/dataset_abc.py
DRecPy/Dataset/dataset_factory.py
DRecPy/Dataset/db_dataset.py
DRecPy/Dataset/file_utils.py
DRecPy/Dataset/integrated_datasets.py
DRecPy/Dataset/mem_dataset-backup.py
DRecPy/Dataset/mem_dataset.py
DRecPy/Dataset/mem_dataset_new.py
DRecPy/Dataset/mem_dataset_numpy.py
DRecPy/Evaluation/__init__.py
DRecPy/Evaluation/loss_tracker.py
DRecPy/Evaluation/Metrics/__init__.py
DRecPy/Evaluation/Metrics/metric_abc.py
DRecPy/Evaluation/Metrics/ranking.py
DRecPy/Evaluation/Metrics/regression.py
DRecPy/Evaluation/Processes/__init__.py
DRecPy/Evaluation/Processes/predictive_evaluation.py
DRecPy/Evaluation/Processes/ranking_evaluation.py
DRecPy/Evaluation/Processes/recommendation_evaluation.py
DRecPy/Evaluation/Splits/__init__.py
DRecPy/Evaluation/Splits/leave_k_out.py
DRecPy/Evaluation/Splits/matrix_split.py
DRecPy/Evaluation/Splits/random_split.py
DRecPy/Recommender/__init__.py
DRecPy/Recommender/caser.py
DRecPy/Recommender/cdae.py
DRecPy/Recommender/dmf.py
DRecPy/Recommender/neumf.py
DRecPy/Recommender/recommender_abc.py
DRecPy/Recommender/test.py
DRecPy/Recommender/Baseline/__init__.py
DRecPy/Recommender/Baseline/aggregation.py
DRecPy/Recommender/Baseline/base_knn.py
DRecPy/Recommender/Baseline/item_knn.py
DRecPy/Recommender/Baseline/similarity.py
DRecPy/Recommender/Baseline/user_knn.py
DRecPy/Recommender/Baseline/user_knn_new.py
DRecPy/Recommender/EarlyStopping/__init__.py
DRecPy/Recommender/EarlyStopping/early_stopping_rule_abc.py
DRecPy/Recommender/EarlyStopping/max_validation_value_rule.py
DRecPy/Sampler/__init__.py
DRecPy/Sampler/list_sampler.py
DRecPy/Sampler/point_sampler.py
DRecPy-0.2.2.dist-info/LICENSE.md
DRecPy-0.2.2.dist-info/METADATA
DRecPy-0.2.2.dist-info/WHEEL
DRecPy-0.2.2.dist-info/top_level.txt
DRecPy-0.2.2.dist-info/RECORD
