Metadata-Version: 2.1
Name: DRecPy
Version: 0.2.2
Summary: Deep Recommenders with Python: A Python framework for building Deep Learning based Recommender Systems
Home-page: https://github.com/fabioiuri/DRecPy
Author: Fabio Colaço
Author-email: fabioiuri@live.com
License: UNKNOWN
Keywords: recommender,recommendation,system,machine learning,deep learning
Platform: UNKNOWN
Classifier: Intended Audience :: Developers
Classifier: Intended Audience :: Education
Classifier: Intended Audience :: Science/Research
Classifier: License :: OSI Approved :: MIT License
Classifier: Programming Language :: Python :: 3
Classifier: Development Status :: 3 - Alpha
Classifier: Topic :: Scientific/Engineering
Requires-Dist: scipy (<2,>=1.2)
Requires-Dist: joblib (<1,>=0.13)
Requires-Dist: pandas (<1,>=0.24)
Requires-Dist: numpy (<2,>=1.16)
Requires-Dist: scikit-learn (>=0.20<1)
Requires-Dist: tensorflow (>=2.0<3)
Requires-Dist: matplotlib
Requires-Dist: tqdm
